{"id": "940ad910-eafa-436c-8009-8b5083843c1f", "object_id": "hva:2011-064-048", "ldesResource": null, "type": "asset", "objectNumber": [{"key": "object_number", "value": "2011-064-048", "__typename": "Metadata"}], "title": [{"key": "title", "value": "Affiche voor Driekoningencarnaval, Zottegem, 1968-1969", "__typename": "Metadata"}], "description": [{"key": "description", "value": "", "__typename": "Metadata"}], "scopeNote": [], "publicationStatus": [], "metadataCollection": [{"label": "objectnummer", "nested": false, "data": [{"value": "2011-064-048", "unMappedKey": null, "label": "objectnummer", "nestedMetaData": null, "__typename": "Metadata"}], "__typename": "MetadataCollection"}], "primary_mediafile": "a0037a7f1ceeed487bdc272c80b14955-2011-064-048.tif", "primary_mediafile_location": "https://api.collectie.gent/storage/v1/download/a0037a7f1ceeed487bdc272c80b14955-2011-064-048.tif", "primary_transcode": "d6ebc948b609892a91e86a3800ea96df-transcode-2011-064-048.jpg", "primary_transcode_location": "https://api.collectie.gent/storage/v1/download/d6ebc948b609892a91e86a3800ea96df-transcode-2011-064-048.jpg", "mediafiles": [{"_id": "mediafiles/fef8a253-5c4b-42d0-857b-f138a7384b3f", "filename": "a0037a7f1ceeed487bdc272c80b14955-2011-064-048.tif", "original_file_location": "https://api.collectie.gent/storage/v1/download/a0037a7f1ceeed487bdc272c80b14955-2011-064-048.tif", "transcode_filename": "d6ebc948b609892a91e86a3800ea96df-transcode-2011-064-048.jpg", "transcode_file_location": "https://api.collectie.gent/storage/v1/download/d6ebc948b609892a91e86a3800ea96df-transcode-2011-064-048.jpg", "thumbnail_file_location": "https://api.collectie.gent/iiif/image/iiif/3/d6ebc948b609892a91e86a3800ea96df-transcode-2011-064-048.jpg/full/,150/0/default.jpg", "mimetype": "image/tiff", "mediatype": {"type": "image/tiff", "mime": "IMGTIFF", "image": true, "audio": false, "video": false, "pdf": false, "__typename": "MimeType"}, "metadata": [{"key": "rights", "value": "In Copyright", "__typename": "MediaFileMetadata"}, {"key": "source", "value": "Huis van Alijn", "__typename": "MediaFileMetadata"}, {"key": "publication_status", "value": "publiek", "__typename": "MediaFileMetadata"}], "__typename": "MediaFile"}], "relations": [{"key": "entities/94c0a4e6-0511-473b-939a-93c5fa989d9a", "type": "isIn", "label": "MaterieelDing.beheerder", "value": "Huis van Alijn", "__typename": "Relation"}, {"key": "entities/7cf08a57-53a8-40c8-8771-04443419f1a2", "type": "components", "label": "Entiteit.classificatie", "value": "Classificatie", "__typename": "Relation"}, {"key": "entities/5d3a8e15-4c21-4e9f-bcf7-caa88676534d", "type": "components", "label": "objectnaam", "value": "affiche", "__typename": "Relation"}, {"key": "entities/189d0c9c-f4e7-4223-b603-fbfd4bb388ee", "type": "components", "label": "MaterieelDing.productie", "value": "Productie", "__typename": "Relation"}, {"key": "entities/928af13e-2e6e-4c57-8712-aaa0cbfc19d6", "type": "components", "label": "vervaardiger", "value": "Gemeentelijk Feestcomit\u00e9 Zottegem", "__typename": "Relation"}, {"key": "entities/dade400d-6a35-4303-a7c3-3fc70c91ee9b", "type": "components", "label": "vervaardiging.plaats", "value": "Zottegem", "__typename": "Relation"}, {"key": "entities/ab7d080c-6ffe-4f13-b799-ded56a7e4f8d", "type": "components", "label": "MaterieelDing.productie", "value": "Productie", "__typename": "Relation"}, {"key": "entities/1c895516-0876-49d9-a3cd-43ff1f7fa25e", "type": "components", "label": "vervaardiger", "value": "V.V.V. De Zwalmboorden", "__typename": "Relation"}, {"key": "entities/54de59b5-ea74-4856-b26a-ac045998eab8", "type": "components", "label": "MensgemaaktObject.draagt", "value": "InformatieObject", "__typename": "Relation"}, {"key": "entities/b8368ec2-e9fa-45c0-b444-6afff4c339c3", "type": "components", "label": "associatie.onderwerp", "value": "carnaval", "__typename": "Relation"}, {"key": "entities/41169c4e-e36a-4ebf-9830-64b17b43014e", "type": "components", "label": "associatie.onderwerp", "value": "Driekoningen", "__typename": "Relation"}, {"key": "entities/dade400d-6a35-4303-a7c3-3fc70c91ee9b", "type": "components", "label": "associatie.onderwerp", "value": "Zottegem", "__typename": "Relation"}, {"key": "entities/ef63dec6-a37e-46f8-974d-2fe298f86d5c", "type": "components", "label": "associatie.periode", "value": "jaren 1960", "__typename": "Relation"}, {"key": "entities/7c82457f-74dc-4912-8533-3b829e210b21", "type": "components", "label": "inhoud.onderwerp", "value": "oog", "__typename": "Relation"}], "__typename": "Entity"}