{"id": "cf851a5e-6d8f-4661-bbcf-f4945867ef9e", "object_id": "hva:2007-119-096", "ldesResource": null, "type": "asset", "objectNumber": [{"key": "object_number", "value": "2007-119-096", "__typename": "Metadata"}], "title": [{"key": "title", "value": "Handmixer HM 3060 van Philips in de originele productverpakking", "__typename": "Metadata"}], "description": [{"key": "description", "value": "Elektrische handmixer met drie snelheden van Philips. Langzaam kloppen voor onder andere sausen en sterk spattende vloeistoffen, het mengen van meel door beslag of het scheppen van stijfgeslagen eiwitten. Een matige snelheid voor het mengen van yoghurt, vloeibaar beslag, mayonaise, omelet en soepen en een hoge snelheid voor onder andere het stijfkloppen van eiwit, milkshakes en cakedeeg.\r\nIn originele productverpakking, met handleiding.", "__typename": "Metadata"}], "scopeNote": [], "publicationStatus": [], "metadataCollection": [{"label": "objectnummer", "nested": false, "data": [{"value": "2007-119-096", "unMappedKey": null, "label": "objectnummer", "nestedMetaData": null, "__typename": "Metadata"}], "__typename": "MetadataCollection"}], "primary_mediafile": "38bc6b084850305874214f48f79e7a7e-2007-119-096.tif", "primary_mediafile_location": "https://api.collectie.gent/storage/v1/download/38bc6b084850305874214f48f79e7a7e-2007-119-096.tif", "primary_transcode": "a1ddf9425cd49e092bc0cccd440846f7-transcode-2007-119-096.jpg", "primary_transcode_location": "https://api.collectie.gent/storage/v1/download/a1ddf9425cd49e092bc0cccd440846f7-transcode-2007-119-096.jpg", "mediafiles": [{"_id": "mediafiles/4c8cffbe-be32-407b-acc2-3962ce054cbb", "filename": "38bc6b084850305874214f48f79e7a7e-2007-119-096.tif", "original_file_location": "https://api.collectie.gent/storage/v1/download/38bc6b084850305874214f48f79e7a7e-2007-119-096.tif", "transcode_filename": "a1ddf9425cd49e092bc0cccd440846f7-transcode-2007-119-096.jpg", "transcode_file_location": "https://api.collectie.gent/storage/v1/download/a1ddf9425cd49e092bc0cccd440846f7-transcode-2007-119-096.jpg", "thumbnail_file_location": "https://api.collectie.gent/iiif/image/iiif/3/a1ddf9425cd49e092bc0cccd440846f7-transcode-2007-119-096.jpg/full/,150/0/default.jpg", "mimetype": "image/tiff", "mediatype": {"type": "image/tiff", "mime": "IMGTIFF", "image": true, "audio": false, "video": false, "pdf": false, "__typename": "MimeType"}, "metadata": [{"key": "rights", "value": "In Copyright", "__typename": "MediaFileMetadata"}, {"key": "source", "value": "Huis van Alijn", "__typename": "MediaFileMetadata"}, {"key": "publication_status", "value": "publiek", "__typename": "MediaFileMetadata"}], "__typename": "MediaFile"}], "relations": [{"key": "entities/94c0a4e6-0511-473b-939a-93c5fa989d9a", "type": "isIn", "label": "MaterieelDing.beheerder", "value": "Huis van Alijn", "__typename": "Relation"}, {"key": "entities/5fa3f8bc-4ef2-4a96-985d-78937f36287f", "type": "components", "label": "Entiteit.classificatie", "value": "Classificatie", "__typename": "Relation"}, {"key": "entities/303440fd-ac45-40fe-8bff-aff3c483c8e5", "type": "components", "label": "objectnaam", "value": "mixer (kookgerei)", "__typename": "Relation"}, {"key": "entities/420e51f5-85d1-446e-b54b-7a194feab80a", "type": "components", "label": "Entiteit.classificatie", "value": "Classificatie", "__typename": "Relation"}, {"key": "entities/6b70f8a0-a522-46a8-bb61-9e1525dcd595", "type": "components", "label": "object_category", "value": "keukengerei", "__typename": "Relation"}, {"key": "entities/4f090a65-6902-4d97-bafc-8b3e44bada1e", "type": "components", "label": "MaterieelDing.productie", "value": "Productie", "__typename": "Relation"}, {"key": "entities/1ed95f6c-4807-4601-a608-087778522e03", "type": "components", "label": "vervaardiger", "value": "Philips", "__typename": "Relation"}, {"key": "entities/bc05d72a-711e-4446-8321-230d7a4d071e", "type": "components", "label": "vervaardiging.plaats", "value": "Eindhoven", "__typename": "Relation"}, {"key": "entities/5953b351-9601-4474-bd4b-cb0f9d79f07e", "type": "components", "label": "MensgemaaktObject.draagt", "value": "InformatieObject", "__typename": "Relation"}, {"key": "entities/e491bd0e-ebc7-49fa-b24f-3129ad9c6c9e", "type": "components", "label": "associatie.onderwerp", "value": "keuken", "__typename": "Relation"}, {"key": "entities/a7b80d0d-123b-4c21-9b4a-f18587861070", "type": "components", "label": "associatie.onderwerp", "value": "voedsel", "__typename": "Relation"}, {"key": "entities/078a7f32-e98a-4ff8-88eb-cdb63ac92ab6", "type": "components", "label": "associatie.onderwerp", "value": "huishouden", "__typename": "Relation"}, {"key": "entities/ef63dec6-a37e-46f8-974d-2fe298f86d5c", "type": "components", "label": "associatie.periode", "value": "jaren 1960", "__typename": "Relation"}, {"key": "entities/a66b1752-9e66-4c11-b1ea-af386345bb5c", "type": "parent", "label": null, "value": null, "__typename": "Relation"}], "__typename": "Entity"}