{"id": "e38cb642-702f-424e-814a-83f0fe10816d", "object_id": "hva:VI-0012-0028", "ldesResource": null, "type": "asset", "objectNumber": [{"key": "object_number", "value": "VI-0012-0028", "__typename": "Metadata"}], "title": [{"key": "title", "value": "Fancy fair op een school, Afsnee", "__typename": "Metadata"}], "description": [{"key": "description", "value": "Jaarmarkt met attracties op de gemeentelijke school in Afsnee. Op de binnenkoer van de nonnenschool zijn er allerhande standjes en kraampjes met verschillende spelletjes, onder andere houten vissen vangen, raddraaien en ringen werpen.", "__typename": "Metadata"}], "scopeNote": [], "publicationStatus": [], "metadataCollection": [{"label": "objectnummer", "nested": false, "data": [{"value": "VI-0012-0028", "unMappedKey": null, "label": "objectnummer", "nestedMetaData": null, "__typename": "Metadata"}], "__typename": "MetadataCollection"}], "primary_mediafile": "164363391f3fb94edfff9fc483384400-VI-0012-0028.mov", "primary_mediafile_location": "https://api.collectie.gent/storage/v1/download/164363391f3fb94edfff9fc483384400-VI-0012-0028.mov", "primary_transcode": "d753920d8561f450ec8bc3fdbf9563c1-transcode-VI-0012-0028.mp4", "primary_transcode_location": "https://api.collectie.gent/storage/v1/download/d753920d8561f450ec8bc3fdbf9563c1-transcode-VI-0012-0028.mp4", "mediafiles": [{"_id": "mediafiles/764db4b0-2371-4f85-85a6-af0e3e0871f5", "filename": "164363391f3fb94edfff9fc483384400-VI-0012-0028.mov", "original_file_location": "https://api.collectie.gent/storage/v1/download/164363391f3fb94edfff9fc483384400-VI-0012-0028.mov", "transcode_filename": "d753920d8561f450ec8bc3fdbf9563c1-transcode-VI-0012-0028.mp4", "transcode_file_location": "https://api.collectie.gent/storage/v1/download/d753920d8561f450ec8bc3fdbf9563c1-transcode-VI-0012-0028.mp4", "thumbnail_file_location": "https://api.collectie.gent/iiif/image/iiif/3/d753920d8561f450ec8bc3fdbf9563c1-transcode-VI-0012-0028.mp4/full/,150/0/default.jpg", "mimetype": "video/quicktime", "mediatype": {"type": "video/quicktime", "mime": "VIDEOMOV", "image": false, "audio": false, "video": true, "pdf": false, "__typename": "MimeType"}, "metadata": [{"key": "rights", "value": "In Copyright - non-commercial use permitted", "__typename": "MediaFileMetadata"}, {"key": "source", "value": "Huis van Alijn", "__typename": "MediaFileMetadata"}, {"key": "publication_status", "value": "publiek", "__typename": "MediaFileMetadata"}], "__typename": "MediaFile"}], "relations": [{"key": "entities/94c0a4e6-0511-473b-939a-93c5fa989d9a", "type": "isIn", "label": "MaterieelDing.beheerder", "value": "Huis van Alijn", "__typename": "Relation"}, {"key": "entities/9eafeea1-e85d-417b-ab5c-2fdd1ab64b26", "type": "components", "label": "Entiteit.classificatie", "value": "Classificatie", "__typename": "Relation"}, {"key": "entities/032f4a53-8406-4f73-8167-a46e9091579c", "type": "components", "label": "objectnaam", "value": "videoproductie", "__typename": "Relation"}, {"key": "entities/2d329abc-bba4-4a11-a996-267d6794c0c5", "type": "components", "label": "MaterieelDing.productie", "value": "Productie", "__typename": "Relation"}, {"key": "entities/8e3b0bcf-e004-47be-9e86-558af698df9a", "type": "components", "label": "vervaardiger", "value": "Huis van Alijn", "__typename": "Relation"}, {"key": "entities/048168ce-5278-4ffc-ace0-dd25f3890955", "type": "components", "label": "MensgemaaktObject.draagt", "value": "InformatieObject", "__typename": "Relation"}, {"key": "entities/4b98c685-8808-4a4d-bf5b-2fb51d46012d", "type": "components", "label": "associatie.onderwerp", "value": "onderwijs", "__typename": "Relation"}, {"key": "entities/5fd13110-0aab-412a-bc86-601f317bc5ac", "type": "components", "label": "associatie.onderwerp", "value": "school", "__typename": "Relation"}, {"key": "entities/5f7da460-ca5c-4ee0-8848-24354791dd39", "type": "components", "label": "associatie.onderwerp", "value": "speelgoed", "__typename": "Relation"}, {"key": "entities/cfc87e52-cd72-4cc3-aef1-a0c73f187fa7", "type": "components", "label": "associatie.onderwerp", "value": "Afsnee", "__typename": "Relation"}, {"key": "entities/6c37a305-99e8-4a10-951c-54b415a953a9", "type": "components", "label": "associatie.periode", "value": "jaren 1950", "__typename": "Relation"}], "__typename": "Entity"}