{"id": "4dcb37b0-a390-48ee-b5ca-ff8ce4fb947d", "object_id": "hva:FO-40-00610", "ldesResource": null, "type": "asset", "objectNumber": [{"key": "object_number", "value": "FO-40-00610", "__typename": "Metadata"}], "title": [{"key": "title", "value": "Bruidspaar Marie-Jos\u00e8phe en Frans verlaat de kerk, 1947", "__typename": "Metadata"}], "description": [{"key": "description", "value": "", "__typename": "Metadata"}], "scopeNote": [], "publicationStatus": [], "metadataCollection": [{"label": "objectnummer", "nested": false, "data": [{"value": "FO-40-00610", "unMappedKey": null, "label": "objectnummer", "nestedMetaData": null, "__typename": "Metadata"}], "__typename": "MetadataCollection"}], "primary_mediafile": "d5529e0d569b87dc1bf81ce2a290f0bd-FO-40-00610.tif", "primary_mediafile_location": "https://api.collectie.gent/storage/v1/download/d5529e0d569b87dc1bf81ce2a290f0bd-FO-40-00610.tif", "primary_transcode": "00cd2cc2e74d8d84e1e12a6b916fc4f8-transcode-FO-40-00610.jpg", "primary_transcode_location": "https://api.collectie.gent/storage/v1/download/00cd2cc2e74d8d84e1e12a6b916fc4f8-transcode-FO-40-00610.jpg", "mediafiles": [{"_id": "mediafiles/083ed2a6-a8c8-4f5a-bd71-1a53eda86030", "filename": "d5529e0d569b87dc1bf81ce2a290f0bd-FO-40-00610.tif", "original_file_location": "https://api.collectie.gent/storage/v1/download/d5529e0d569b87dc1bf81ce2a290f0bd-FO-40-00610.tif", "transcode_filename": "00cd2cc2e74d8d84e1e12a6b916fc4f8-transcode-FO-40-00610.jpg", "transcode_file_location": "https://api.collectie.gent/storage/v1/download/00cd2cc2e74d8d84e1e12a6b916fc4f8-transcode-FO-40-00610.jpg", "thumbnail_file_location": "https://api.collectie.gent/iiif/image/iiif/3/00cd2cc2e74d8d84e1e12a6b916fc4f8-transcode-FO-40-00610.jpg/full/,150/0/default.jpg", "mimetype": "image/tiff", "mediatype": {"type": "image/tiff", "mime": "IMGTIFF", "image": true, "audio": false, "video": false, "pdf": false, "__typename": "MimeType"}, "metadata": [{"key": "rights", "value": "In Copyright - unknown rightsholder", "__typename": "MediaFileMetadata"}, {"key": "source", "value": "Huis van Alijn", "__typename": "MediaFileMetadata"}, {"key": "publication_status", "value": "publiek", "__typename": "MediaFileMetadata"}], "__typename": "MediaFile"}], "relations": [{"key": "entities/94c0a4e6-0511-473b-939a-93c5fa989d9a", "type": "isIn", "label": "MaterieelDing.beheerder", "value": "Huis van Alijn", "__typename": "Relation"}, {"key": "entities/44f61871-fbe4-4c14-a090-46792db84e18", "type": "components", "label": "Entiteit.classificatie", "value": "Classificatie", "__typename": "Relation"}, {"key": "entities/efd98907-9143-42f7-a891-3945e089c8a0", "type": "components", "label": "objectnaam", "value": "digitale afbeelding", "__typename": "Relation"}, {"key": "entities/64defe5f-53d9-445c-aaa2-0c9734421358", "type": "components", "label": "MensgemaaktObject.draagt", "value": "InformatieObject", "__typename": "Relation"}, {"key": "entities/28d8fd89-9f94-4edf-bc7e-acf2d8de4d76", "type": "components", "label": "associatie.onderwerp", "value": "huwelijk", "__typename": "Relation"}, {"key": "entities/1cc3ff15-6ef8-456d-a346-e638394f6d08", "type": "components", "label": "associatie.onderwerp", "value": "kerk", "__typename": "Relation"}, {"key": "entities/3464ae98-3d40-4b86-a4e9-6c70c34a1345", "type": "components", "label": "associatie.periode", "value": "jaren 1940", "__typename": "Relation"}, {"key": "entities/0b2b3739-cd9b-4536-85f2-fa515e441118", "type": "components", "label": "inhoud.onderwerp", "value": "bruidspaar", "__typename": "Relation"}, {"key": "entities/4280147f-c805-4e7b-814a-1099c75c795a", "type": "components", "label": "inhoud.onderwerp", "value": "bruidsboeket", "__typename": "Relation"}], "__typename": "Entity"}