{"id": "1208a3aa-7f12-43ab-97b9-8111772046b3", "object_id": "hva:1977-147", "ldesResource": null, "type": "asset", "objectNumber": [{"key": "object_number", "value": "1977-147", "__typename": "Metadata"}], "title": [{"key": "title", "value": "Porseleinen inktpot versierd met blauwe chinoiserie\u00ebn", "__typename": "Metadata"}], "description": [{"key": "description", "value": "", "__typename": "Metadata"}], "scopeNote": [], "publicationStatus": [], "metadataCollection": [{"label": "objectnummer", "nested": false, "data": [{"value": "1977-147", "unMappedKey": null, "label": "objectnummer", "nestedMetaData": null, "__typename": "Metadata"}], "__typename": "MetadataCollection"}], "primary_mediafile": "f1f3560283debc3d90dcc0a3305f5105-1977-147.tif", "primary_mediafile_location": "https://api.collectie.gent/storage/v1/download/f1f3560283debc3d90dcc0a3305f5105-1977-147.tif", "primary_transcode": "0b85428a09ef47f76d99380e3368ca47-transcode-1977-147.jpg", "primary_transcode_location": "https://api.collectie.gent/storage/v1/download/0b85428a09ef47f76d99380e3368ca47-transcode-1977-147.jpg", "mediafiles": [{"_id": "mediafiles/7eebda2c-8b5e-4193-8bf7-ac82f61ca1f1", "filename": "f1f3560283debc3d90dcc0a3305f5105-1977-147.tif", "original_file_location": "https://api.collectie.gent/storage/v1/download/f1f3560283debc3d90dcc0a3305f5105-1977-147.tif", "transcode_filename": "0b85428a09ef47f76d99380e3368ca47-transcode-1977-147.jpg", "transcode_file_location": "https://api.collectie.gent/storage/v1/download/0b85428a09ef47f76d99380e3368ca47-transcode-1977-147.jpg", "thumbnail_file_location": "https://api.collectie.gent/iiif/image/iiif/3/0b85428a09ef47f76d99380e3368ca47-transcode-1977-147.jpg/full/,150/0/default.jpg", "mimetype": "image/tiff", "mediatype": {"type": "image/tiff", "mime": "IMGTIFF", "image": true, "audio": false, "video": false, "pdf": false, "__typename": "MimeType"}, "metadata": [{"key": "rights", "value": "CC0 1.0", "__typename": "MediaFileMetadata"}, {"key": "source", "value": "Huis van Alijn", "__typename": "MediaFileMetadata"}, {"key": "publication_status", "value": "publiek", "__typename": "MediaFileMetadata"}], "__typename": "MediaFile"}], "relations": [{"key": "entities/94c0a4e6-0511-473b-939a-93c5fa989d9a", "type": "isIn", "label": "MaterieelDing.beheerder", "value": "Huis van Alijn", "__typename": "Relation"}, {"key": "entities/0e189ae2-6787-447c-be12-6a39c8d05007", "type": "components", "label": "Entiteit.classificatie", "value": "Classificatie", "__typename": "Relation"}, {"key": "entities/d5e161c7-832a-4f88-8158-30e3e0766cf2", "type": "components", "label": "objectnaam", "value": "inktpot", "__typename": "Relation"}, {"key": "entities/a06b2bd7-7b91-4f5a-8b8d-79032f9bf0c2", "type": "components", "label": "Entiteit.classificatie", "value": "Classificatie", "__typename": "Relation"}, {"key": "entities/8792d994-8897-4346-8250-723319488fcb", "type": "components", "label": "object_category", "value": "schrijfbenodigdheden", "__typename": "Relation"}, {"key": "entities/31ef8407-e6a6-4e6d-b078-aefba379f96e", "type": "components", "label": "MensgemaaktObject.draagt", "value": "InformatieObject", "__typename": "Relation"}, {"key": "entities/4b98c685-8808-4a4d-bf5b-2fb51d46012d", "type": "components", "label": "associatie.onderwerp", "value": "onderwijs", "__typename": "Relation"}, {"key": "entities/5fd13110-0aab-412a-bc86-601f317bc5ac", "type": "components", "label": "associatie.onderwerp", "value": "school", "__typename": "Relation"}], "__typename": "Entity"}