{"id": "7d830ff1-44d0-4df8-baa9-a034b750710a", "object_id": "hva:2004-247-102", "ldesResource": null, "type": "asset", "objectNumber": [{"key": "object_number", "value": "2004-247-102", "__typename": "Metadata"}], "title": [{"key": "title", "value": "Stakende arbeiders op wagen op het Sint-Pietersplein, Gent, 1893", "__typename": "Metadata"}], "description": [{"key": "description", "value": "Stakende arbeiders zijn samengekomen op het Sint-Pietersplein in Gent tijdens de algemene staking van april 1893. Rechts buiten het beeld houden socialistische kopstukken een toespraak. Een aantal mensen heeft plaatsgenomen op een houten wagen om de sprekers beter te kunnen zien. De kleine jongen vooraan kijkt ge\u00efnteresseerd naar wat er op de wagen gebeurt.", "__typename": "Metadata"}], "scopeNote": [], "publicationStatus": [], "metadataCollection": [{"label": "objectnummer", "nested": false, "data": [{"value": "2004-247-102", "unMappedKey": null, "label": "objectnummer", "nestedMetaData": null, "__typename": "Metadata"}], "__typename": "MetadataCollection"}], "primary_mediafile": "0e756f3aded5f32f5deeaeb15e5b6db9-2004-247-102.tif", "primary_mediafile_location": "https://api.collectie.gent/storage/v1/download/0e756f3aded5f32f5deeaeb15e5b6db9-2004-247-102.tif", "primary_transcode": "1f70c8e272db1a2f39a7e08ca658adc3-transcode-2004-247-102.jpg", "primary_transcode_location": "https://api.collectie.gent/storage/v1/download/1f70c8e272db1a2f39a7e08ca658adc3-transcode-2004-247-102.jpg", "mediafiles": [{"_id": "mediafiles/e9bf27cf-734f-4f93-8050-f3300427fb10", "filename": "0e756f3aded5f32f5deeaeb15e5b6db9-2004-247-102.tif", "original_file_location": "https://api.collectie.gent/storage/v1/download/0e756f3aded5f32f5deeaeb15e5b6db9-2004-247-102.tif", "transcode_filename": "1f70c8e272db1a2f39a7e08ca658adc3-transcode-2004-247-102.jpg", "transcode_file_location": "https://api.collectie.gent/storage/v1/download/1f70c8e272db1a2f39a7e08ca658adc3-transcode-2004-247-102.jpg", "thumbnail_file_location": "https://api.collectie.gent/iiif/image/iiif/3/1f70c8e272db1a2f39a7e08ca658adc3-transcode-2004-247-102.jpg/full/,150/0/default.jpg", "mimetype": "image/tiff", "mediatype": {"type": "image/tiff", "mime": "IMGTIFF", "image": true, "audio": false, "video": false, "pdf": false, "__typename": "MimeType"}, "metadata": [{"key": "rights", "value": "Public Domain Mark 1.0", "__typename": "MediaFileMetadata"}, {"key": "source", "value": "Huis van Alijn", "__typename": "MediaFileMetadata"}, {"key": "publication_status", "value": "publiek", "__typename": "MediaFileMetadata"}], "__typename": "MediaFile"}], "relations": [{"key": "entities/94c0a4e6-0511-473b-939a-93c5fa989d9a", "type": "isIn", "label": "MaterieelDing.beheerder", "value": "Huis van Alijn", "__typename": "Relation"}, {"key": "entities/c4b015f5-580d-4dd6-bc57-a27c2c9fb82e", "type": "components", "label": "Entiteit.classificatie", "value": "Classificatie", "__typename": "Relation"}, {"key": "entities/451b6191-87e2-4114-a14d-ac8d935e56a2", "type": "components", "label": "objectnaam", "value": "glasnegatief", "__typename": "Relation"}, {"key": "entities/873fd2c5-9c96-4b89-a0f0-f7eac759da60", "type": "components", "label": "MaterieelDing.productie", "value": "Productie", "__typename": "Relation"}, {"key": "entities/8de2b2bc-383f-4440-867f-4ef9037991a3", "type": "components", "label": "vervaardiger", "value": "Vander Haeghen, Arnold", "__typename": "Relation"}, {"key": "entities/fd5f3888-ad34-4d4f-87f5-9bc2ab4d49a7", "type": "components", "label": "vervaardiging.plaats", "value": "Gent", "__typename": "Relation"}, {"key": "entities/675dd0e5-a415-4b81-bf86-65fd5bc115eb", "type": "components", "label": "MensgemaaktObject.draagt", "value": "InformatieObject", "__typename": "Relation"}, {"key": "entities/07c91021-4d03-4a71-822d-b7dccf0620b6", "type": "components", "label": "associatie.onderwerp", "value": "Sint-Pietersplein (Gent)", "__typename": "Relation"}, {"key": "entities/5c0d1554-6ad8-414a-99e1-f79d1088e955", "type": "components", "label": "associatie.onderwerp", "value": "protesteren", "__typename": "Relation"}, {"key": "entities/73fc8307-0a8c-4cea-bd0b-38ecf84180e5", "type": "components", "label": "associatie.onderwerp", "value": "arbeid", "__typename": "Relation"}, {"key": "entities/eada66b3-bc68-4b33-b0eb-c32ca226dced", "type": "components", "label": "associatie.onderwerp", "value": "vervoer", "__typename": "Relation"}, {"key": "entities/4f16cc6c-686f-40c1-b09c-fa78227f4ab1", "type": "components", "label": "associatie.onderwerp", "value": "Sint-Pietersplein (Gent)", "__typename": "Relation"}, {"key": "entities/fd5f3888-ad34-4d4f-87f5-9bc2ab4d49a7", "type": "components", "label": "associatie.onderwerp", "value": "Gent", "__typename": "Relation"}, {"key": "entities/e8899a0c-dd0c-4976-a78d-7302c46c1688", "type": "components", "label": "associatie.periode", "value": "jaren 1890", "__typename": "Relation"}, {"key": "entities/a9f63ce1-d1b0-4055-a20e-aeed0a866f37", "type": "components", "label": "associatie.periode", "value": "19de eeuw", "__typename": "Relation"}, {"key": "entities/867f65e9-5fa8-4319-a967-d8707a1ab7c6", "type": "parent", "label": null, "value": null, "__typename": "Relation"}], "__typename": "Entity"}