{"id": "5d991ed0-62db-4c0d-a12f-e3bcfe023cd1", "object_id": "industriemuseum:V25049", "ldesResource": null, "type": "asset", "objectNumber": [{"key": "object_number", "value": "V25049", "__typename": "Metadata"}], "title": [{"key": "title", "value": "Elektrische typemachine van het merk Olivetti", "__typename": "Metadata"}], "description": [{"key": "description", "value": "Draagbare elektrische schrijfmachine van het merk Olivetti, type Underwood 660.  Van het type frontstrike en met azertytoetsenbord.", "__typename": "Metadata"}], "scopeNote": [], "publicationStatus": [], "metadataCollection": [{"label": "objectnummer", "nested": false, "data": [{"value": "V25049", "unMappedKey": null, "label": "objectnummer", "nestedMetaData": null, "__typename": "Metadata"}], "__typename": "MetadataCollection"}, {"label": "hoogte", "nested": false, "data": [{"value": "14 cm", "unMappedKey": null, "label": "hoogte", "nestedMetaData": null, "__typename": "Metadata"}], "__typename": "MetadataCollection"}, {"label": "breedte", "nested": false, "data": [{"value": "40 cm", "unMappedKey": null, "label": "breedte", "nestedMetaData": null, "__typename": "Metadata"}], "__typename": "MetadataCollection"}, {"label": "diepte", "nested": false, "data": [{"value": "48 cm", "unMappedKey": null, "label": "diepte", "nestedMetaData": null, "__typename": "Metadata"}], "__typename": "MetadataCollection"}], "primary_mediafile": "0d8fb91bfd3b5d3893d2fe2b0382397d-V25049.jpg", "primary_mediafile_location": "https://api.collectie.gent/storage/v1/download/0d8fb91bfd3b5d3893d2fe2b0382397d-V25049.jpg", "primary_transcode": "0cdb357f55739ad0b3c085b8b41fce4f-transcode-V25049.jpg", "primary_transcode_location": "https://api.collectie.gent/storage/v1/download/0cdb357f55739ad0b3c085b8b41fce4f-transcode-V25049.jpg", "mediafiles": [{"_id": "mediafiles/99346262-f5bb-4099-bce8-1228648ade63", "filename": "0d8fb91bfd3b5d3893d2fe2b0382397d-V25049.jpg", "original_file_location": "https://api.collectie.gent/storage/v1/download/0d8fb91bfd3b5d3893d2fe2b0382397d-V25049.jpg", "transcode_filename": "0cdb357f55739ad0b3c085b8b41fce4f-transcode-V25049.jpg", "transcode_file_location": "https://api.collectie.gent/storage/v1/download/0cdb357f55739ad0b3c085b8b41fce4f-transcode-V25049.jpg", "thumbnail_file_location": "https://api.collectie.gent/iiif/image/iiif/3/0cdb357f55739ad0b3c085b8b41fce4f-transcode-V25049.jpg/full/,150/0/default.jpg", "mimetype": "image/jpeg", "mediatype": {"type": "image/jpeg", "mime": "IMGJPG", "image": true, "audio": false, "video": false, "pdf": false, "__typename": "MimeType"}, "metadata": [{"key": "rights", "value": "In Copyright", "__typename": "MediaFileMetadata"}, {"key": "source", "value": "Industriemuseum", "__typename": "MediaFileMetadata"}, {"key": "publication_status", "value": "publiek", "__typename": "MediaFileMetadata"}], "__typename": "MediaFile"}], "relations": [{"key": "entities/07670944-3244-4132-8b3d-0a57cf67c8d6", "type": "isIn", "label": "MaterieelDing.beheerder", "value": "Industriemuseum", "__typename": "Relation"}, {"key": "entities/c1ead59d-1aa6-4e75-9bfb-17b02fe65ea2", "type": "components", "label": "collectie", "value": "informatie en communicatie", "__typename": "Relation"}, {"key": "entities/95b494a7-5fdd-4939-a8ad-3c248a376ef9", "type": "components", "label": "collectie", "value": "kantoor", "__typename": "Relation"}, {"key": "entities/aee921b5-da76-44f9-8b1f-e5f3223dfd74", "type": "components", "label": "MaterieelDing.bestaatUit", "value": "machine", "__typename": "Relation"}, {"key": "entities/2356d05a-1ed5-4fa2-b720-0ece0b548a7c", "type": "components", "label": "materiaal", "value": "kunststof", "__typename": "Relation"}, {"key": "entities/cba4bb01-eb96-4a14-a175-98d3339be4dc", "type": "components", "label": "MaterieelDing.bestaatUit", "value": "onderdelen", "__typename": "Relation"}, {"key": "entities/769ff128-137d-4ab5-980f-6195ffb5e06c", "type": "components", "label": "materiaal", "value": "metaal", "__typename": "Relation"}, {"key": "entities/4a1c10c6-558d-483c-8ba7-a1886db8599b", "type": "components", "label": "Entiteit.classificatie", "value": "Classificatie", "__typename": "Relation"}, {"key": "entities/5fa311f6-ecd9-4cca-b387-480865939cf0", "type": "components", "label": "object_category", "value": "kantoormachines", "__typename": "Relation"}, {"key": "entities/5b75f18b-8d03-4d79-a849-9fd263541c7a", "type": "components", "label": "Entiteit.classificatie", "value": "Classificatie", "__typename": "Relation"}, {"key": "entities/594aaec9-a732-403f-9241-fee634a099b8", "type": "components", "label": "objectnaam", "value": "schrijfmachine", "__typename": "Relation"}, {"key": "entities/fcc01aa3-fbee-45e2-a08b-57bbf7502728", "type": "components", "label": "MaterieelDing.productie", "value": "Productie", "__typename": "Relation"}, {"key": "entities/fb1ad5d5-08b1-4d6d-96dc-d0e05578f454", "type": "components", "label": "vervaardiger", "value": "Olivetti", "__typename": "Relation"}, {"key": "entities/e28fda0b-dbb0-4700-ab83-aef4062e17e2", "type": "components", "label": "vervaardiging.plaats", "value": "Spanje", "__typename": "Relation"}, {"key": "entities/d990c51f-4832-4c51-b382-2f99fe772e7f", "type": "components", "label": "MensgemaaktObject.draagt", "value": "Taalobject", "__typename": "Relation"}, {"key": "entities/4541e668-da98-4187-8b19-d558724a9b7b", "type": "components", "label": "MensgemaaktObject.draagt", "value": "Taalobject", "__typename": "Relation"}, {"key": "entities/82268aca-ead0-43da-b156-b9e54a0c247b", "type": "components", "label": "MensgemaaktObject.draagt", "value": "InformatieObject", "__typename": "Relation"}, {"key": "entities/e4ff4523-c1e1-450a-bedc-242e50f6f354", "type": "components", "label": "associatie.onderwerp", "value": "informatie en communicatie", "__typename": "Relation"}, {"key": "entities/4acd7053-3456-488d-b196-f51a4f3909d9", "type": "components", "label": "associatie.onderwerp", "value": "kantoor", "__typename": "Relation"}, {"key": "entities/594aaec9-a732-403f-9241-fee634a099b8", "type": "components", "label": "associatie.onderwerp", "value": "schrijfmachine", "__typename": "Relation"}, {"key": "entities/fb1ad5d5-08b1-4d6d-96dc-d0e05578f454", "type": "components", "label": "associatie.persoon", "value": "Olivetti", "__typename": "Relation"}, {"key": "entities/4cf0408f-6eea-47e5-ac29-60f8a3286743", "type": "components", "label": "associatie.periode", "value": "einde 20ste eeuw", "__typename": "Relation"}], "__typename": "Entity"}