{"id": "21a8c2eb-4344-42c2-8fa9-54fae5b1bec2", "object_id": "industriemuseum:V26343", "ldesResource": null, "type": "asset", "objectNumber": [{"key": "object_number", "value": "V26343", "__typename": "Metadata"}], "title": [{"key": "title", "value": "Doosje voor medicijn tegen zenuwpijnen", "__typename": "Metadata"}], "description": [{"key": "description", "value": "Kartonnen doosje gebruikt als verpakking voor pillen of tabletten voor het bestrijden van zenuwpijen. Vervaardigd door apotheker Jean Baetsl\u00e9 in Gent.", "__typename": "Metadata"}], "scopeNote": [], "publicationStatus": [], "metadataCollection": [{"label": "objectnummer", "nested": false, "data": [{"value": "V26343", "unMappedKey": null, "label": "objectnummer", "nestedMetaData": null, "__typename": "Metadata"}], "__typename": "MetadataCollection"}, {"label": "hoogte", "nested": false, "data": [{"value": "2.7 cm", "unMappedKey": null, "label": "hoogte", "nestedMetaData": null, "__typename": "Metadata"}], "__typename": "MetadataCollection"}, {"label": "breedte", "nested": false, "data": [{"value": "10 cm", "unMappedKey": null, "label": "breedte", "nestedMetaData": null, "__typename": "Metadata"}], "__typename": "MetadataCollection"}, {"label": "diepte", "nested": false, "data": [{"value": "2.7 cm", "unMappedKey": null, "label": "diepte", "nestedMetaData": null, "__typename": "Metadata"}], "__typename": "MetadataCollection"}], "primary_mediafile": "c9d2830ab5ca2043f1d2adec89f7bf05-V26343.jpg", "primary_mediafile_location": "https://api.collectie.gent/storage/v1/download/c9d2830ab5ca2043f1d2adec89f7bf05-V26343.jpg", "primary_transcode": "f8e81ee9d6ac125c2a01e63081ad1817-transcode-V26343.jpg", "primary_transcode_location": "https://api.collectie.gent/storage/v1/download/f8e81ee9d6ac125c2a01e63081ad1817-transcode-V26343.jpg", "mediafiles": [{"_id": "mediafiles/906f3880-c53c-44b2-bd94-017a31e7527c", "filename": "c9d2830ab5ca2043f1d2adec89f7bf05-V26343.jpg", "original_file_location": "https://api.collectie.gent/storage/v1/download/c9d2830ab5ca2043f1d2adec89f7bf05-V26343.jpg", "transcode_filename": "f8e81ee9d6ac125c2a01e63081ad1817-transcode-V26343.jpg", "transcode_file_location": "https://api.collectie.gent/storage/v1/download/f8e81ee9d6ac125c2a01e63081ad1817-transcode-V26343.jpg", "thumbnail_file_location": "https://api.collectie.gent/iiif/image/iiif/3/f8e81ee9d6ac125c2a01e63081ad1817-transcode-V26343.jpg/full/,150/0/default.jpg", "mimetype": "image/jpeg", "mediatype": {"type": "image/jpeg", "mime": "IMGJPG", "image": true, "audio": false, "video": false, "pdf": false, "__typename": "MimeType"}, "metadata": [{"key": "rights", "value": "In Copyright - unknown rightsholder", "__typename": "MediaFileMetadata"}, {"key": "source", "value": "Industriemuseum", "__typename": "MediaFileMetadata"}, {"key": "publication_status", "value": "publiek", "__typename": "MediaFileMetadata"}], "__typename": "MediaFile"}], "relations": [{"key": "entities/07670944-3244-4132-8b3d-0a57cf67c8d6", "type": "isIn", "label": "MaterieelDing.beheerder", "value": "Industriemuseum", "__typename": "Relation"}, {"key": "entities/4166e84a-e519-4436-9709-a8309e103cc5", "type": "components", "label": "collectie", "value": "medische en paramedische sector", "__typename": "Relation"}, {"key": "entities/5c09d254-748f-44e6-8091-f40c99b78f00", "type": "components", "label": "Entiteit.classificatie", "value": "Classificatie", "__typename": "Relation"}, {"key": "entities/30037e48-0ec0-4995-9b8f-dec633721ae2", "type": "components", "label": "object_category", "value": "productverpakkingen", "__typename": "Relation"}, {"key": "entities/6f5ceb41-b017-46bd-91a3-49c94b0ed8fd", "type": "components", "label": "Entiteit.classificatie", "value": "Classificatie", "__typename": "Relation"}, {"key": "entities/f1438ee0-e8fe-4e75-958c-6152e857158a", "type": "components", "label": "objectnaam", "value": "doos (houder)", "__typename": "Relation"}, {"key": "entities/a98679b0-d6af-4fac-8294-017da4516520", "type": "components", "label": "MaterieelDing.productie", "value": "Productie", "__typename": "Relation"}, {"key": "entities/6c9fe2a8-5a1f-4b27-9fb2-982778d5cc41", "type": "components", "label": "vervaardiger", "value": "Baetsl\u00e9 Jean", "__typename": "Relation"}, {"key": "entities/fd5f3888-ad34-4d4f-87f5-9bc2ab4d49a7", "type": "components", "label": "vervaardiging.plaats", "value": "Gent", "__typename": "Relation"}, {"key": "entities/8782ae41-3166-4ec3-beff-ece90aef82c9", "type": "components", "label": "MensgemaaktObject.draagt", "value": "Taalobject", "__typename": "Relation"}, {"key": "entities/52196c35-ea5d-4e55-be6e-763a308b614f", "type": "components", "label": "MensgemaaktObject.draagt", "value": "InformatieObject", "__typename": "Relation"}, {"key": "entities/f1438ee0-e8fe-4e75-958c-6152e857158a", "type": "components", "label": "associatie.onderwerp", "value": "doos (houder)", "__typename": "Relation"}, {"key": "entities/f89a5029-8176-4574-86a1-8a6d66dc5933", "type": "components", "label": "associatie.periode", "value": "1ste helft 20ste eeuw", "__typename": "Relation"}, {"key": "entities/4b0b3aee-3f5c-403d-95a5-b4a45ba3c0f6", "type": "components", "label": "materiaal", "value": "karton", "__typename": "Relation"}], "__typename": "Entity"}