{"id": "cc9225f5-b7ab-4f50-8e9c-2a45524a8f1b", "object_id": "industriemuseum:V08738", "ldesResource": null, "type": "asset", "objectNumber": [{"key": "object_number", "value": "V08738", "__typename": "Metadata"}], "title": [{"key": "title", "value": "Witte tropenhelm", "__typename": "Metadata"}], "description": [{"key": "description", "value": "", "__typename": "Metadata"}], "scopeNote": [], "publicationStatus": [], "metadataCollection": [{"label": "objectnummer", "nested": false, "data": [{"value": "V08738", "unMappedKey": null, "label": "objectnummer", "nestedMetaData": null, "__typename": "Metadata"}], "__typename": "MetadataCollection"}, {"label": "hoogte", "nested": false, "data": [{"value": "17 cm", "unMappedKey": null, "label": "hoogte", "nestedMetaData": null, "__typename": "Metadata"}], "__typename": "MetadataCollection"}, {"label": "breedte", "nested": false, "data": [{"value": "30 cm", "unMappedKey": null, "label": "breedte", "nestedMetaData": null, "__typename": "Metadata"}], "__typename": "MetadataCollection"}, {"label": "lengte", "nested": false, "data": [{"value": "38 cm", "unMappedKey": null, "label": "lengte", "nestedMetaData": null, "__typename": "Metadata"}], "__typename": "MetadataCollection"}], "primary_mediafile": "3c1e245b47696201b2906f96eb3320a8-V08738.jpg", "primary_mediafile_location": "https://api.collectie.gent/storage/v1/download/3c1e245b47696201b2906f96eb3320a8-V08738.jpg", "primary_transcode": "ce9f4144a0b499509aacb93c2428a8f1-transcode-V08738.jpg", "primary_transcode_location": "https://api.collectie.gent/storage/v1/download/ce9f4144a0b499509aacb93c2428a8f1-transcode-V08738.jpg", "mediafiles": [{"_id": "mediafiles/3690589a-b25c-439e-803c-5e8ecd2f63b8", "filename": "3c1e245b47696201b2906f96eb3320a8-V08738.jpg", "original_file_location": "https://api.collectie.gent/storage/v1/download/3c1e245b47696201b2906f96eb3320a8-V08738.jpg", "transcode_filename": "ce9f4144a0b499509aacb93c2428a8f1-transcode-V08738.jpg", "transcode_file_location": "https://api.collectie.gent/storage/v1/download/ce9f4144a0b499509aacb93c2428a8f1-transcode-V08738.jpg", "thumbnail_file_location": "https://api.collectie.gent/iiif/image/iiif/3/ce9f4144a0b499509aacb93c2428a8f1-transcode-V08738.jpg/full/,150/0/default.jpg", "mimetype": "image/jpeg", "mediatype": {"type": "image/jpeg", "mime": "IMGJPG", "image": true, "audio": false, "video": false, "pdf": false, "__typename": "MimeType"}, "metadata": [{"key": "rights", "value": "In Copyright - unknown rightsholder", "__typename": "MediaFileMetadata"}, {"key": "source", "value": "Industriemuseum", "__typename": "MediaFileMetadata"}, {"key": "publication_status", "value": "publiek", "__typename": "MediaFileMetadata"}], "__typename": "MediaFile"}], "relations": [{"key": "entities/07670944-3244-4132-8b3d-0a57cf67c8d6", "type": "isIn", "label": "MaterieelDing.beheerder", "value": "Industriemuseum", "__typename": "Relation"}, {"key": "entities/f3a31f59-b0e8-466f-b10d-edfc60c379e7", "type": "components", "label": "collectie", "value": "textiel", "__typename": "Relation"}, {"key": "entities/fa7aa014-604e-4044-a859-046ac59d46a9", "type": "components", "label": "collectie", "value": "kleding en accessoires", "__typename": "Relation"}, {"key": "entities/3b77ca12-5bcd-4ea9-acf8-42aa1c866e29", "type": "components", "label": "Entiteit.classificatie", "value": "Classificatie", "__typename": "Relation"}, {"key": "entities/70ce882d-a8ca-4d6e-9fe3-8c8d5910b53f", "type": "components", "label": "object_category", "value": "hoofddeksels", "__typename": "Relation"}, {"key": "entities/f07431f3-ce43-40d2-ac61-a0dad3bf0330", "type": "components", "label": "Entiteit.classificatie", "value": "Classificatie", "__typename": "Relation"}, {"key": "entities/c15f0fa0-f6b5-43b3-9044-ca1e00ba6777", "type": "components", "label": "objectnaam", "value": "tropenhelm", "__typename": "Relation"}, {"key": "entities/b4c2d4d5-c24e-4770-8462-4c5e440a7a05", "type": "components", "label": "MensgemaaktObject.draagt", "value": "InformatieObject", "__typename": "Relation"}, {"key": "entities/6f39ec62-39dd-4be2-a64f-6f856683f151", "type": "components", "label": "associatie.onderwerp", "value": "textiel", "__typename": "Relation"}, {"key": "entities/fa7aa014-604e-4044-a859-046ac59d46a9", "type": "components", "label": "associatie.onderwerp", "value": "kleding en accessoires", "__typename": "Relation"}, {"key": "entities/70ce882d-a8ca-4d6e-9fe3-8c8d5910b53f", "type": "components", "label": "associatie.onderwerp", "value": "hoofddeksels", "__typename": "Relation"}, {"key": "entities/ac17f4e5-7a07-4b07-922b-85ab8c8d6a3c", "type": "components", "label": "associatie.periode", "value": "2de kwart 20ste eeuw", "__typename": "Relation"}, {"key": "entities/5f002900-7045-4910-9322-116c69841619", "type": "components", "label": "materiaal", "value": "canvas", "__typename": "Relation"}], "__typename": "Entity"}