{"id": "4cdecf18-4e62-4397-94e9-e70cc7842497", "object_id": "archiefgent:MA_SCMS_FO_01885", "ldesResource": null, "type": "asset", "objectNumber": [{"key": "object_number", "value": "MA_SCMS_FO_01885", "__typename": "Metadata"}], "title": [{"key": "title", "value": "Gent: Sint-Veerleplein: Gravensteen, 1889-1913", "__typename": "Metadata"}], "description": [{"key": "description", "value": "De Romaanse Galerij van het Gravensteen tijdens de restauratie ervan. Links staan enkele personen te poseren voor de camera.\r\n\r\nOp de achterzijde een stempel van Commissie der Monumenten (SCMS).", "__typename": "Metadata"}], "scopeNote": [], "publicationStatus": [], "metadataCollection": [{"label": "objectnummer", "nested": false, "data": [{"value": "MA_SCMS_FO_01885", "unMappedKey": null, "label": "objectnummer", "nestedMetaData": null, "__typename": "Metadata"}], "__typename": "MetadataCollection"}], "primary_mediafile": "7a1f5fa1dd496f07a232068dda41abcc-MA_SCMS_FO_01885.tif", "primary_mediafile_location": "https://api.collectie.gent/storage/v1/download/7a1f5fa1dd496f07a232068dda41abcc-MA_SCMS_FO_01885.tif", "primary_transcode": "5c05ec1c4b2ed33fb3827d66361aa80d-transcode-MA_SCMS_FO_01885.jpg", "primary_transcode_location": "https://api.collectie.gent/storage/v1/download/5c05ec1c4b2ed33fb3827d66361aa80d-transcode-MA_SCMS_FO_01885.jpg", "mediafiles": [{"_id": "mediafiles/7dc693d3-4d3b-4fcd-b190-738c55f6345d", "filename": "7a1f5fa1dd496f07a232068dda41abcc-MA_SCMS_FO_01885.tif", "original_file_location": "https://api.collectie.gent/storage/v1/download/7a1f5fa1dd496f07a232068dda41abcc-MA_SCMS_FO_01885.tif", "transcode_filename": "5c05ec1c4b2ed33fb3827d66361aa80d-transcode-MA_SCMS_FO_01885.jpg", "transcode_file_location": "https://api.collectie.gent/storage/v1/download/5c05ec1c4b2ed33fb3827d66361aa80d-transcode-MA_SCMS_FO_01885.jpg", "thumbnail_file_location": "https://api.collectie.gent/iiif/image/iiif/3/5c05ec1c4b2ed33fb3827d66361aa80d-transcode-MA_SCMS_FO_01885.jpg/full/,150/0/default.jpg", "mimetype": "image/tiff", "mediatype": {"type": "image/tiff", "mime": "IMGTIFF", "image": true, "audio": false, "video": false, "pdf": false, "__typename": "MimeType"}, "metadata": [{"key": "rights", "value": "Public Domain Mark 1.0", "__typename": "MediaFileMetadata"}, {"key": "source", "value": "Archief Gent", "__typename": "MediaFileMetadata"}, {"key": "publication_status", "value": "publiek", "__typename": "MediaFileMetadata"}], "__typename": "MediaFile"}], "relations": [{"key": "entities/358c1bdc-bcd7-45ab-8b93-e2cd85d21aca", "type": "isIn", "label": "MaterieelDing.beheerder", "value": "Archief Gent", "__typename": "Relation"}, {"key": "entities/b87f9451-3d7b-446c-aeb2-87b9cf6d71e5", "type": "components", "label": "collectie", "value": "Foto\u2019s Stedelijke Commissie voor Monumenten en Stadsgezichten (MA_SCMS_FO)", "__typename": "Relation"}, {"key": "entities/80f139ce-248d-41b3-b45c-dfb5dd0c9c7c", "type": "components", "label": "MaterieelDing.bestaatUit", "value": "binnenste afmetingen", "__typename": "Relation"}, {"key": "entities/d4552ed7-d53e-40bd-8c40-51236393770d", "type": "components", "label": "MaterieelDing.isOvergedragenBijVerwerving", "value": "Verwerving", "__typename": "Relation"}, {"key": "entities/852b04cd-5445-4330-ba26-a16fd83f488f", "type": "components", "label": "Entiteit.classificatie", "value": "Classificatie", "__typename": "Relation"}, {"key": "entities/91587e6c-05a9-4a58-90ee-b520cef70868", "type": "components", "label": "object_category", "value": "foto's SCMS", "__typename": "Relation"}, {"key": "entities/8fb943c1-62cd-457c-85aa-34b3cc6b5075", "type": "components", "label": "Entiteit.classificatie", "value": "Classificatie", "__typename": "Relation"}, {"key": "entities/0936cfa4-6137-4c66-ad61-0c9b5b9482b1", "type": "components", "label": "objectnaam", "value": "foto", "__typename": "Relation"}, {"key": "entities/505edaa9-342b-41ff-94cb-83293ffbe7b3", "type": "components", "label": "objectnaam", "value": "foto", "__typename": "Relation"}, {"key": "entities/069a6a60-f83e-47cc-9b9a-3c3df235e3fb", "type": "components", "label": "Entiteit.classificatie", "value": "Classificatie", "__typename": "Relation"}, {"key": "entities/91587e6c-05a9-4a58-90ee-b520cef70868", "type": "components", "label": "Classificatie.toegekendType", "value": "foto's SCMS", "__typename": "Relation"}, {"key": "entities/73cb9f5d-c157-412d-94f6-67f2cf7ec677", "type": "components", "label": "Entiteit.classificatie", "value": "Classificatie", "__typename": "Relation"}, {"key": "entities/ea76502f-6ad9-4b6b-8f05-f4220fd600d9", "type": "components", "label": "Classificatie.toegekendType", "value": "Modern Archief", "__typename": "Relation"}, {"key": "entities/ae5cdefc-bbbf-4cdc-aee1-66f455bbedb6", "type": "components", "label": "Entiteit.classificatie", "value": "Classificatie", "__typename": "Relation"}, {"key": "entities/a063021c-61f0-49c8-b0c7-c963fffd2d1a", "type": "components", "label": "Classificatie.toegekendType", "value": "Stedelijke Commissie voor Monumenten en Stadsgezichten (SCMS)", "__typename": "Relation"}, {"key": "entities/dc9a1741-c80d-4152-a93b-8c715d288e40", "type": "components", "label": "Entiteit.classificatie", "value": "Classificatie", "__typename": "Relation"}, {"key": "entities/52f9b59a-e8d3-480e-84a5-ccabd726deb0", "type": "components", "label": "Classificatie.toegekendType", "value": "Gravensteen", "__typename": "Relation"}, {"key": "entities/12d946e6-f99c-46ce-9f21-d4659ff61216", "type": "components", "label": "Entiteit.classificatie", "value": "Classificatie", "__typename": "Relation"}, {"key": "entities/15a14c65-70bd-4e03-9169-5afdc782e9d2", "type": "components", "label": "Classificatie.toegekendType", "value": "oude stadsgezichten", "__typename": "Relation"}, {"key": "entities/a5f38583-19fa-42da-bb34-3873857b45b4", "type": "components", "label": "Entiteit.classificatie", "value": "Classificatie", "__typename": "Relation"}, {"key": "entities/d8437514-b8ff-45ea-924b-0928cba2fa2d", "type": "components", "label": "MaterieelDing.productie", "value": "Productie", "__typename": "Relation"}, {"key": "entities/bd90f2e5-7949-417e-8ea0-b189a9b1acd9", "type": "components", "label": "vervaardiger", "value": "Casier, Joseph", "__typename": "Relation"}, {"key": "entities/ce285207-6196-4857-8db4-f9a4d8663980", "type": "components", "label": "MensgemaaktObject.draagt", "value": "InformatieObject", "__typename": "Relation"}, {"key": "entities/13975d34-0f8f-46d0-990f-ecc9d9c1e1be", "type": "components", "label": "associatie.onderwerp", "value": "Sint-Veerleplein", "__typename": "Relation"}, {"key": "entities/0a21604f-da82-4a97-9fbf-f0af5ca9de4a", "type": "components", "label": "associatie.onderwerp", "value": "Sint-Veerleplein", "__typename": "Relation"}, {"key": "entities/5d52b755-9784-4e92-961b-93c41ffcff0d", "type": "components", "label": "associatie.onderwerp", "value": "Binnenstad", "__typename": "Relation"}, {"key": "entities/da087e40-82ee-4292-a856-f84b76256164", "type": "components", "label": "associatie.onderwerp", "value": "Gent", "__typename": "Relation"}, {"key": "entities/db8a6cd2-5755-4afd-adac-ab2d054d8b78", "type": "components", "label": "inhoud.onderwerp", "value": "burcht", "__typename": "Relation"}], "__typename": "Entity"}