{"id": "f318cfc4-e607-4559-8f9b-111ca29a868f", "object_id": "archiefgent:MA_SCMS_FO_01257", "ldesResource": null, "type": "asset", "objectNumber": [{"key": "object_number", "value": "MA_SCMS_FO_01257", "__typename": "Metadata"}], "title": [{"key": "title", "value": "Gent: Zaaimansstraat (nu Dobbelslot), 1901", "__typename": "Metadata"}], "description": [{"key": "description", "value": "De Zaaimansstraat met links op de foto een gevelkapelletje. Verschillende personen poseren voor de camera.\r\n\r\nHandtekening van de fotograaf: foto van Constant D\u2019Hoy op opzetkarton, met de blinddrukstempel van Charles D\u2019Hoy - photographe Gand. Op de voorkant een stempel van Archief der Stad Gent. Op de achterzijde opnieuw een stempel van Archief der Stad Gent, alsook een stempel van Commissie der Monumenten (SCMS).", "__typename": "Metadata"}], "scopeNote": [], "publicationStatus": [], "metadataCollection": [{"label": "objectnummer", "nested": false, "data": [{"value": "MA_SCMS_FO_01257", "unMappedKey": null, "label": "objectnummer", "nestedMetaData": null, "__typename": "Metadata"}], "__typename": "MetadataCollection"}], "primary_mediafile": "f92a1e8f5e48c63f870f55b997b7c4d8-MA_SCMS_FO_01257.tif", "primary_mediafile_location": "https://api.collectie.gent/storage/v1/download/f92a1e8f5e48c63f870f55b997b7c4d8-MA_SCMS_FO_01257.tif", "primary_transcode": "12ab8f78a61fc54e7159bfd50adc0a40-transcode-MA_SCMS_FO_01257.jpg", "primary_transcode_location": "https://api.collectie.gent/storage/v1/download/12ab8f78a61fc54e7159bfd50adc0a40-transcode-MA_SCMS_FO_01257.jpg", "mediafiles": [{"_id": "mediafiles/14ef0487-d3ff-40f9-9ba4-461164a84b98", "filename": "f92a1e8f5e48c63f870f55b997b7c4d8-MA_SCMS_FO_01257.tif", "original_file_location": "https://api.collectie.gent/storage/v1/download/f92a1e8f5e48c63f870f55b997b7c4d8-MA_SCMS_FO_01257.tif", "transcode_filename": "12ab8f78a61fc54e7159bfd50adc0a40-transcode-MA_SCMS_FO_01257.jpg", "transcode_file_location": "https://api.collectie.gent/storage/v1/download/12ab8f78a61fc54e7159bfd50adc0a40-transcode-MA_SCMS_FO_01257.jpg", "thumbnail_file_location": "https://api.collectie.gent/iiif/image/iiif/3/12ab8f78a61fc54e7159bfd50adc0a40-transcode-MA_SCMS_FO_01257.jpg/full/,150/0/default.jpg", "mimetype": "image/tiff", "mediatype": {"type": "image/tiff", "mime": "IMGTIFF", "image": true, "audio": false, "video": false, "pdf": false, "__typename": "MimeType"}, "metadata": [{"key": "rights", "value": "Public Domain Mark 1.0", "__typename": "MediaFileMetadata"}, {"key": "source", "value": "Archief Gent", "__typename": "MediaFileMetadata"}, {"key": "publication_status", "value": "publiek", "__typename": "MediaFileMetadata"}], "__typename": "MediaFile"}], "relations": [{"key": "entities/358c1bdc-bcd7-45ab-8b93-e2cd85d21aca", "type": "isIn", "label": "MaterieelDing.beheerder", "value": "Archief Gent", "__typename": "Relation"}, {"key": "entities/b87f9451-3d7b-446c-aeb2-87b9cf6d71e5", "type": "components", "label": "collectie", "value": "Foto\u2019s Stedelijke Commissie voor Monumenten en Stadsgezichten (MA_SCMS_FO)", "__typename": "Relation"}, {"key": "entities/198b542c-3c46-4566-a95d-116fbb4aac2a", "type": "components", "label": "MaterieelDing.bestaatUit", "value": "binnenste afmetingen", "__typename": "Relation"}, {"key": "entities/715c4286-8e94-45d9-8635-cc4d282a4de7", "type": "components", "label": "MaterieelDing.isOvergedragenBijVerwerving", "value": "Verwerving", "__typename": "Relation"}, {"key": "entities/4c7f320b-4de4-483f-b845-f2b30ef15ecb", "type": "components", "label": "Entiteit.classificatie", "value": "Classificatie", "__typename": "Relation"}, {"key": "entities/91587e6c-05a9-4a58-90ee-b520cef70868", "type": "components", "label": "object_category", "value": "foto's SCMS", "__typename": "Relation"}, {"key": "entities/926c3b05-5352-4d55-a848-cce9d7df70db", "type": "components", "label": "Entiteit.classificatie", "value": "Classificatie", "__typename": "Relation"}, {"key": "entities/0936cfa4-6137-4c66-ad61-0c9b5b9482b1", "type": "components", "label": "objectnaam", "value": "foto", "__typename": "Relation"}, {"key": "entities/505edaa9-342b-41ff-94cb-83293ffbe7b3", "type": "components", "label": "objectnaam", "value": "foto", "__typename": "Relation"}, {"key": "entities/ffb0ea21-2e42-4268-a76b-2e30c78a88a2", "type": "components", "label": "Entiteit.classificatie", "value": "Classificatie", "__typename": "Relation"}, {"key": "entities/91587e6c-05a9-4a58-90ee-b520cef70868", "type": "components", "label": "Classificatie.toegekendType", "value": "foto's SCMS", "__typename": "Relation"}, {"key": "entities/facda086-cdd0-4b1d-8a8c-91ac86f264d0", "type": "components", "label": "Entiteit.classificatie", "value": "Classificatie", "__typename": "Relation"}, {"key": "entities/ea76502f-6ad9-4b6b-8f05-f4220fd600d9", "type": "components", "label": "Classificatie.toegekendType", "value": "Modern Archief", "__typename": "Relation"}, {"key": "entities/19800cbe-5670-4f93-83aa-567733c7bcf8", "type": "components", "label": "Entiteit.classificatie", "value": "Classificatie", "__typename": "Relation"}, {"key": "entities/a063021c-61f0-49c8-b0c7-c963fffd2d1a", "type": "components", "label": "Classificatie.toegekendType", "value": "Stedelijke Commissie voor Monumenten en Stadsgezichten (SCMS)", "__typename": "Relation"}, {"key": "entities/5676ef20-1ac2-47d3-9d6b-280cab0bbd44", "type": "components", "label": "Entiteit.classificatie", "value": "Classificatie", "__typename": "Relation"}, {"key": "entities/f973a235-8483-430d-8c56-c74b4aa6d95d", "type": "components", "label": "Classificatie.toegekendType", "value": "gevelrij", "__typename": "Relation"}, {"key": "entities/a6c9ca5b-89fa-4a6e-894a-3a7b82f8b3de", "type": "components", "label": "Entiteit.classificatie", "value": "Classificatie", "__typename": "Relation"}, {"key": "entities/15a14c65-70bd-4e03-9169-5afdc782e9d2", "type": "components", "label": "Classificatie.toegekendType", "value": "oude stadsgezichten", "__typename": "Relation"}, {"key": "entities/f99e909f-0a23-4144-8c13-10b811ee4741", "type": "components", "label": "Entiteit.classificatie", "value": "Classificatie", "__typename": "Relation"}, {"key": "entities/77966ed2-30c7-4e35-96e7-07a9113cd3e2", "type": "components", "label": "MaterieelDing.productie", "value": "Productie", "__typename": "Relation"}, {"key": "entities/154a49e3-0752-480a-acac-4999d85e1a17", "type": "components", "label": "vervaardiger", "value": "d'Hoy, Constant", "__typename": "Relation"}, {"key": "entities/653a3299-5ca1-4089-9003-d051fa9bb17e", "type": "components", "label": "MensgemaaktObject.draagt", "value": "InformatieObject", "__typename": "Relation"}, {"key": "entities/27ba3fa8-8c30-4928-af0d-40eb3a145741", "type": "components", "label": "associatie.onderwerp", "value": "Zaaimansstraat", "__typename": "Relation"}, {"key": "entities/61384e97-2ff8-4a52-bb10-9897336466a1", "type": "components", "label": "associatie.onderwerp", "value": "Dobbelslot", "__typename": "Relation"}, {"key": "entities/61a5d0b9-89d9-4d94-8e95-3748c1d5209e", "type": "components", "label": "associatie.onderwerp", "value": "Sluizeken-Tolhuis-Ham", "__typename": "Relation"}, {"key": "entities/da087e40-82ee-4292-a856-f84b76256164", "type": "components", "label": "associatie.onderwerp", "value": "Gent", "__typename": "Relation"}, {"key": "entities/e80addf5-f6ae-4253-a167-a8fc798ee314", "type": "components", "label": "associatie.periode", "value": "jaren 1900", "__typename": "Relation"}], "__typename": "Entity"}