{"id": "f9c2ee34-47ac-4513-bc96-c336e39a8792", "object_id": "stam:09508", "ldesResource": null, "type": "asset", "objectNumber": [{"key": "object_number", "value": "09508", "__typename": "Metadata"}], "title": [{"key": "title", "value": "Olie- en azijnstel", "__typename": "Metadata"}], "description": [{"key": "description", "value": "Olie- en azijnstel op vier gekrulde pootjes met opengewerkte korfjes (de flesjes zijn verdwenen) en versierd handvat in bloemvorm. Op het onderste verbindingsstuk staat het merk van de engel en St. Michiel en M. Walravens", "__typename": "Metadata"}], "scopeNote": [], "publicationStatus": [], "metadataCollection": [{"label": "objectnummer", "nested": false, "data": [{"value": "09508", "unMappedKey": null, "label": "objectnummer", "nestedMetaData": null, "__typename": "Metadata"}], "__typename": "MetadataCollection"}, {"label": "hoogte", "nested": false, "data": [{"value": "24.7 cm", "unMappedKey": null, "label": "hoogte", "nestedMetaData": null, "__typename": "Metadata"}], "__typename": "MetadataCollection"}, {"label": "breedte", "nested": false, "data": [{"value": "20.6 cm", "unMappedKey": null, "label": "breedte", "nestedMetaData": null, "__typename": "Metadata"}], "__typename": "MetadataCollection"}, {"label": "diepte", "nested": false, "data": [{"value": "10 cm", "unMappedKey": null, "label": "diepte", "nestedMetaData": null, "__typename": "Metadata"}], "__typename": "MetadataCollection"}], "primary_mediafile": "2f2cc833c03ca3e47e4565c4b8406866-09508.tif", "primary_mediafile_location": "https://api.collectie.gent/storage/v1/download/2f2cc833c03ca3e47e4565c4b8406866-09508.tif", "primary_transcode": "0db3cbe1c569f6ce2d358ed40d87ee51-transcode-09508.jpg", "primary_transcode_location": "https://api.collectie.gent/storage/v1/download/0db3cbe1c569f6ce2d358ed40d87ee51-transcode-09508.jpg", "mediafiles": [{"_id": "mediafiles/20a141d6-a55a-490d-9be6-ba97526c4aa5", "filename": "2f2cc833c03ca3e47e4565c4b8406866-09508.tif", "original_file_location": "https://api.collectie.gent/storage/v1/download/2f2cc833c03ca3e47e4565c4b8406866-09508.tif", "transcode_filename": "0db3cbe1c569f6ce2d358ed40d87ee51-transcode-09508.jpg", "transcode_file_location": "https://api.collectie.gent/storage/v1/download/0db3cbe1c569f6ce2d358ed40d87ee51-transcode-09508.jpg", "thumbnail_file_location": "https://api.collectie.gent/iiif/image/iiif/3/0db3cbe1c569f6ce2d358ed40d87ee51-transcode-09508.jpg/full/,150/0/default.jpg", "mimetype": "image/tiff", "mediatype": {"type": "image/tiff", "mime": "IMGTIFF", "image": true, "audio": false, "video": false, "pdf": false, "__typename": "MimeType"}, "metadata": [{"key": "rights", "value": "CC0 1.0", "__typename": "MediaFileMetadata"}, {"key": "source", "value": "STAM - Stadsmuseum Gent", "__typename": "MediaFileMetadata"}, {"key": "publication_status", "value": "publiek", "__typename": "MediaFileMetadata"}], "__typename": "MediaFile"}], "relations": [{"key": "entities/f65f1cf0-5fc3-4dd4-a190-60b4166ce8df", "type": "isIn", "label": "MaterieelDing.beheerder", "value": "STAM - Stadsmuseum Gent", "__typename": "Relation"}, {"key": "entities/f980fe13-740f-4ddb-86de-ed0a397dcfcf", "type": "components", "label": "MaterieelDing.isOvergedragenBijVerwerving", "value": "Verwerving", "__typename": "Relation"}, {"key": "entities/6f4a648c-9f71-4b9c-a2ba-5016b976d063", "type": "components", "label": "Entiteit.classificatie", "value": "Classificatie", "__typename": "Relation"}, {"key": "entities/85c9e8bf-f622-427b-8007-8e484227e4b9", "type": "components", "label": "objectnaam", "value": "olie- en azijnstel", "__typename": "Relation"}, {"key": "entities/681d6500-fb99-4d8a-b7d7-65c0fa51617d", "type": "components", "label": "MaterieelDing.productie", "value": "Productie", "__typename": "Relation"}, {"key": "entities/63edbec0-11e2-43dd-85f4-260ef483f8c5", "type": "components", "label": "vervaardiger", "value": "Walravens, M.", "__typename": "Relation"}, {"key": "entities/dccdc06e-f1ef-4e78-a691-6332c921af9c", "type": "components", "label": "techniek", "value": "gieten", "__typename": "Relation"}, {"key": "entities/ffddcf5e-c4bc-4c7a-a2dd-f0561a851467", "type": "components", "label": "techniek", "value": "graveren (inkerven)", "__typename": "Relation"}, {"key": "entities/d8507291-ee34-494a-b733-5311b561ed8e", "type": "components", "label": "vervaardiging.plaats", "value": "Brussel", "__typename": "Relation"}, {"key": "entities/71caaae3-cc30-450f-b606-5daf4e1ff931", "type": "components", "label": "MensgemaaktObject.draagt", "value": "InformatieObject", "__typename": "Relation"}, {"key": "entities/2092c260-63c6-4803-b531-9d372420fe72", "type": "components", "label": "materiaal", "value": "tin", "__typename": "Relation"}], "__typename": "Entity"}